sphinxcontrib_editable-0.0.7-py3.7-nspkg.pth
sphinxcontrib/editable/__init__.py
sphinxcontrib/editable/_version.py
sphinxcontrib/editable/_static/__init__.py
sphinxcontrib/editable/_static/css/__init__.py
sphinxcontrib/editable/_static/css/medium-editor.css
sphinxcontrib/editable/_static/css/medium-editor.min.css
sphinxcontrib/editable/_static/css/themes/__init__.py
sphinxcontrib/editable/_static/css/themes/beagle.css
sphinxcontrib/editable/_static/css/themes/beagle.min.css
sphinxcontrib/editable/_static/css/themes/bootstrap.css
sphinxcontrib/editable/_static/css/themes/bootstrap.min.css
sphinxcontrib/editable/_static/css/themes/default.css
sphinxcontrib/editable/_static/css/themes/default.min.css
sphinxcontrib/editable/_static/css/themes/flat.css
sphinxcontrib/editable/_static/css/themes/flat.min.css
sphinxcontrib/editable/_static/css/themes/mani.css
sphinxcontrib/editable/_static/css/themes/mani.min.css
sphinxcontrib/editable/_static/css/themes/roman.css
sphinxcontrib/editable/_static/css/themes/roman.min.css
sphinxcontrib/editable/_static/css/themes/tim.css
sphinxcontrib/editable/_static/css/themes/tim.min.css
sphinxcontrib/editable/_static/js/__init__.py
sphinxcontrib/editable/_static/js/editable.js
sphinxcontrib/editable/_static/js/medium-editor.js
sphinxcontrib/editable/_static/js/medium-editor.min.js
sphinxcontrib_editable-0.0.7.dist-info/LICENSE
sphinxcontrib_editable-0.0.7.dist-info/METADATA
sphinxcontrib_editable-0.0.7.dist-info/WHEEL
sphinxcontrib_editable-0.0.7.dist-info/namespace_packages.txt
sphinxcontrib_editable-0.0.7.dist-info/pbr.json
sphinxcontrib_editable-0.0.7.dist-info/top_level.txt
sphinxcontrib_editable-0.0.7.dist-info/RECORD
