Metadata-Version: 2.1
Name: sphinxcontrib-editable
Version: 0.0.7
Summary: UNKNOWN
Home-page: UNKNOWN
Author: UNKNOWN
Author-email: UNKNOWN
License: UNKNOWN
Platform: UNKNOWN
Requires-Dist: sphinx
Requires-Dist: sphinx-rtd-theme
Requires-Dist: importlib-resources
